{
    "sectionTitle": "Lungfish",
    "pgId": 25397054,
    "numDataRows": 3,
    "_id": "25397054-8",
    "pgTitle": "Paleobiota of the Chinle Formation",
    "numericColumns": [],
    "tableCaption": "Lungfish",
    "tableHeaders": [
        [
            {
                "textTokens": [],
                "isNumeric": false,
                "tdHtmlString": "<th colspan=\"7\" rowspan=\"1\"> <a href=\"http://www.wikipedia.org/wiki/Dipnoans\" shape=\"rect\">Dipnoans</a> of the Chinle Formation </th>",
                "text": "Dipnoans of the Chinle Formation",
                "subtableID": -1,
                "surfaceLinks": [
                    {
                        "offset": 0,
                        "target": {
                            "language": "en",
                            "redirecting": false,
                            "id": 230330,
                            "title": "Dipnoans",
                            "namesapce": 0
                        },
                        "isInTemplate": false,
                        "locType": "MAIN_TABLE",
                        "surface": "Dipnoans",
                        "inTemplate": false,
                        "endOffset": 8,
                        "linkType": "INTERNAL"
                    }
                ],
                "cellID": -1
            },
            {
                "textTokens": [],
                "isNumeric": false,
                "tdHtmlString": "<th colspan=\"7\" rowspan=\"1\"> <a href=\"http://www.wikipedia.org/wiki/Dipnoans\" shape=\"rect\">Dipnoans</a> of the Chinle Formation </th>",
                "text": "Dipnoans of the Chinle Formation",
                "subtableID": -1,
                "surfaceLinks": [
                    {
                        "offset": 0,
                        "target": {
                            "language": "en",
                            "redirecting": false,
                            "id": 230330,
                            "title": "Dipnoans",
                            "namesapce": 0
                        },
                        "isInTemplate": false,
                        "locType": "MAIN_TABLE",
                        "surface": "Dipnoans",
                        "inTemplate": false,
                        "endOffset": 8,
                        "linkType": "INTERNAL"
                    }
                ],
                "cellID": -1
            },
            {
                "textTokens": [],
                "isNumeric": false,
                "tdHtmlString": "<th colspan=\"7\" rowspan=\"1\"> <a href=\"http://www.wikipedia.org/wiki/Dipnoans\" shape=\"rect\">Dipnoans</a> of the Chinle Formation </th>",
                "text": "Dipnoans of the Chinle Formation",
                "subtableID": -1,
                "surfaceLinks": [
                    {
                        "offset": 0,
                        "target": {
                            "language": "en",
                            "redirecting": false,
                            "id": 230330,
                            "title": "Dipnoans",
                            "namesapce": 0
                        },
                        "isInTemplate": false,
                        "locType": "MAIN_TABLE",
                        "surface": "Dipnoans",
                        "inTemplate": false,
                        "endOffset": 8,
                        "linkType": "INTERNAL"
                    }
                ],
                "cellID": -1
            },
            {
                "textTokens": [],
                "isNumeric": false,
                "tdHtmlString": "<th colspan=\"7\" rowspan=\"1\"> <a href=\"http://www.wikipedia.org/wiki/Dipnoans\" shape=\"rect\">Dipnoans</a> of the Chinle Formation </th>",
                "text": "Dipnoans of the Chinle Formation",
                "subtableID": -1,
                "surfaceLinks": [
                    {
                        "offset": 0,
                        "target": {
                            "language": "en",
                            "redirecting": false,
                            "id": 230330,
                            "title": "Dipnoans",
                            "namesapce": 0
                        },
                        "isInTemplate": false,
                        "locType": "MAIN_TABLE",
                        "surface": "Dipnoans",
                        "inTemplate": false,
                        "endOffset": 8,
                        "linkType": "INTERNAL"
                    }
                ],
                "cellID": -1
            },
            {
                "textTokens": [],
                "isNumeric": false,
                "tdHtmlString": "<th colspan=\"7\" rowspan=\"1\"> <a href=\"http://www.wikipedia.org/wiki/Dipnoans\" shape=\"rect\">Dipnoans</a> of the Chinle Formation </th>",
                "text": "Dipnoans of the Chinle Formation",
                "subtableID": -1,
                "surfaceLinks": [
                    {
                        "offset": 0,
                        "target": {
                            "language": "en",
                            "redirecting": false,
                            "id": 230330,
                            "title": "Dipnoans",
                            "namesapce": 0
                        },
                        "isInTemplate": false,
                        "locType": "MAIN_TABLE",
                        "surface": "Dipnoans",
                        "inTemplate": false,
                        "endOffset": 8,
                        "linkType": "INTERNAL"
                    }
                ],
                "cellID": -1
            },
            {
                "textTokens": [],
                "isNumeric": false,
                "tdHtmlString": "<th colspan=\"7\" rowspan=\"1\"> <a href=\"http://www.wikipedia.org/wiki/Dipnoans\" shape=\"rect\">Dipnoans</a> of the Chinle Formation </th>",
                "text": "Dipnoans of the Chinle Formation",
                "subtableID": -1,
                "surfaceLinks": [
                    {
                        "offset": 0,
                        "target": {
                            "language": "en",
                            "redirecting": false,
                            "id": 230330,
                            "title": "Dipnoans",
                            "namesapce": 0
                        },
                        "isInTemplate": false,
                        "locType": "MAIN_TABLE",
                        "surface": "Dipnoans",
                        "inTemplate": false,
                        "endOffset": 8,
                        "linkType": "INTERNAL"
                    }
                ],
                "cellID": -1
            },
            {
                "textTokens": [],
                "isNumeric": false,
                "tdHtmlString": "<th colspan=\"7\" rowspan=\"1\"> <a href=\"http://www.wikipedia.org/wiki/Dipnoans\" shape=\"rect\">Dipnoans</a> of the Chinle Formation </th>",
                "text": "Dipnoans of the Chinle Formation",
                "subtableID": -1,
                "surfaceLinks": [
                    {
                        "offset": 0,
                        "target": {
                            "language": "en",
                            "redirecting": false,
                            "id": 230330,
                            "title": "Dipnoans",
                            "namesapce": 0
                        },
                        "isInTemplate": false,
                        "locType": "MAIN_TABLE",
                        "surface": "Dipnoans",
                        "inTemplate": false,
                        "endOffset": 8,
                        "linkType": "INTERNAL"
                    }
                ],
                "cellID": -1
            }
        ],
        [
            {
                "textTokens": [],
                "isNumeric": false,
                "tdHtmlString": "<th colspan=\"1\" rowspan=\"1\"> Genus </th>",
                "text": "Genus",
                "subtableID": -1,
                "surfaceLinks": [],
                "cellID": -1
            },
            {
                "textTokens": [],
                "isNumeric": false,
                "tdHtmlString": "<th colspan=\"1\" rowspan=\"1\"> Species </th>",
                "text": "Species",
                "subtableID": -1,
                "surfaceLinks": [],
                "cellID": -1
            },
            {
                "textTokens": [],
                "isNumeric": false,
                "tdHtmlString": "<th colspan=\"1\" rowspan=\"1\"> State </th>",
                "text": "State",
                "subtableID": -1,
                "surfaceLinks": [],
                "cellID": -1
            },
            {
                "textTokens": [],
                "isNumeric": false,
                "tdHtmlString": "<th colspan=\"1\" rowspan=\"1\"> Abundance </th>",
                "text": "Abundance",
                "subtableID": -1,
                "surfaceLinks": [],
                "cellID": -1
            },
            {
                "textTokens": [],
                "isNumeric": false,
                "tdHtmlString": "<th colspan=\"1\" rowspan=\"1\"> Notes </th>",
                "text": "Notes",
                "subtableID": -1,
                "surfaceLinks": [],
                "cellID": -1
            },
            {
                "textTokens": [],
                "isNumeric": false,
                "tdHtmlString": "<th colspan=\"1\" rowspan=\"1\"> Notes </th>",
                "text": "Notes",
                "subtableID": -1,
                "surfaceLinks": [],
                "cellID": -1
            },
            {
                "textTokens": [],
                "isNumeric": false,
                "tdHtmlString": "",
                "text": "",
                "subtableID": -1,
                "surfaceLinks": [],
                "cellID": -1
            }
        ]
    ],
    "tableId": 8,
    "tableData": [
        [
            {
                "textTokens": [],
                "isNumeric": false,
                "tdHtmlString": "<td colspan=\"1\" rowspan=\"2\"> <a href=\"http://www.wikipedia.org/wiki/Arganodus\" shape=\"rect\">Arganodus</a> </td>",
                "text": "Arganodus",
                "subtableID": -1,
                "surfaceLinks": [
                    {
                        "offset": 0,
                        "target": {
                            "language": "en",
                            "redirecting": false,
                            "id": 18440224,
                            "title": "Arganodus",
                            "namesapce": 0
                        },
                        "isInTemplate": false,
                        "locType": "MAIN_TABLE",
                        "surface": "Arganodus",
                        "inTemplate": false,
                        "endOffset": 9,
                        "linkType": "INTERNAL"
                    }
                ],
                "cellID": -1
            },
            {
                "textTokens": [],
                "isNumeric": false,
                "tdHtmlString": "<td colspan=\"1\" rowspan=\"1\"> A. dorotheae </td>",
                "text": "A. dorotheae",
                "subtableID": -1,
                "surfaceLinks": [],
                "cellID": -1
            },
            {
                "textTokens": [],
                "isNumeric": false,
                "tdHtmlString": "<td colspan=\"1\" rowspan=\"1\"> </td>",
                "text": "",
                "subtableID": -1,
                "surfaceLinks": [],
                "cellID": -1
            },
            {
                "textTokens": [],
                "isNumeric": false,
                "tdHtmlString": "<td colspan=\"1\" rowspan=\"1\"> </td>",
                "text": "",
                "subtableID": -1,
                "surfaceLinks": [],
                "cellID": -1
            },
            {
                "textTokens": [],
                "isNumeric": false,
                "tdHtmlString": "<td colspan=\"1\" rowspan=\"1\"> </td>",
                "text": "",
                "subtableID": -1,
                "surfaceLinks": [],
                "cellID": -1
            },
            {
                "textTokens": [],
                "isNumeric": false,
                "tdHtmlString": "<td colspan=\"1\" rowspan=\"1\"> </td>",
                "text": "",
                "subtableID": -1,
                "surfaceLinks": [],
                "cellID": -1
            },
            {
                "textTokens": [],
                "isNumeric": false,
                "tdHtmlString": "",
                "text": "",
                "subtableID": -1,
                "surfaceLinks": [],
                "cellID": -1
            }
        ],
        [
            {
                "textTokens": [],
                "isNumeric": false,
                "tdHtmlString": "<td colspan=\"1\" rowspan=\"2\"> <a href=\"http://www.wikipedia.org/wiki/Arganodus\" shape=\"rect\">Arganodus</a> </td>",
                "text": "Arganodus",
                "subtableID": -1,
                "surfaceLinks": [
                    {
                        "offset": 0,
                        "target": {
                            "language": "en",
                            "redirecting": false,
                            "id": 18440224,
                            "title": "Arganodus",
                            "namesapce": 0
                        },
                        "isInTemplate": false,
                        "locType": "MAIN_TABLE",
                        "surface": "Arganodus",
                        "inTemplate": false,
                        "endOffset": 9,
                        "linkType": "INTERNAL"
                    }
                ],
                "cellID": -1
            },
            {
                "textTokens": [],
                "isNumeric": false,
                "tdHtmlString": "<td colspan=\"1\" rowspan=\"1\"> Indeterminate </td>",
                "text": "Indeterminate",
                "subtableID": -1,
                "surfaceLinks": [],
                "cellID": -1
            },
            {
                "textTokens": [],
                "isNumeric": false,
                "tdHtmlString": "<td colspan=\"1\" rowspan=\"1\"> Arizona </td>",
                "text": "Arizona",
                "subtableID": -1,
                "surfaceLinks": [],
                "cellID": -1
            },
            {
                "textTokens": [],
                "isNumeric": false,
                "tdHtmlString": "<td colspan=\"1\" rowspan=\"1\"> Petrified Forest Sonsela Blue Mesa Mesa Redondo </td>",
                "text": "Petrified Forest Sonsela Blue Mesa Mesa Redondo",
                "subtableID": -1,
                "surfaceLinks": [],
                "cellID": -1
            },
            {
                "textTokens": [],
                "isNumeric": false,
                "tdHtmlString": "<td colspan=\"1\" rowspan=\"1\"> Arganodus toothplates are the most common fossil in the formation from a non-tetrapod. They are evenly distributed across strata, although some individual localities have very high concentrations. </td>",
                "text": "Arganodus toothplates are the most common fossil in the formation from a non-tetrapod. They are evenly distributed across strata, although some individual localities have very high concentrations.",
                "subtableID": -1,
                "surfaceLinks": [],
                "cellID": -1
            },
            {
                "textTokens": [],
                "isNumeric": false,
                "tdHtmlString": "<td colspan=\"1\" rowspan=\"1\"> Most Chinlean Arganodus fossils are isolated tooth plates. </td>",
                "text": "Most Chinlean Arganodus fossils are isolated tooth plates.",
                "subtableID": -1,
                "surfaceLinks": [],
                "cellID": -1
            },
            {
                "textTokens": [],
                "isNumeric": false,
                "tdHtmlString": "",
                "text": "",
                "subtableID": -1,
                "surfaceLinks": [],
                "cellID": -1
            }
        ],
        [
            {
                "textTokens": [],
                "isNumeric": false,
                "tdHtmlString": "<td colspan=\"1\" rowspan=\"1\"> <a href=\"http://www.wikipedia.org/wiki/Ceratodus\" shape=\"rect\">Ceratodus</a> </td>",
                "text": "Ceratodus",
                "subtableID": -1,
                "surfaceLinks": [
                    {
                        "offset": 0,
                        "target": {
                            "language": "en",
                            "redirecting": false,
                            "id": 10641140,
                            "title": "Ceratodus",
                            "namesapce": 0
                        },
                        "isInTemplate": false,
                        "locType": "MAIN_TABLE",
                        "surface": "Ceratodus",
                        "inTemplate": false,
                        "endOffset": 9,
                        "linkType": "INTERNAL"
                    }
                ],
                "cellID": -1
            },
            {
                "textTokens": [],
                "isNumeric": false,
                "tdHtmlString": "<td colspan=\"1\" rowspan=\"1\"> C. dorotheae </td>",
                "text": "C. dorotheae",
                "subtableID": -1,
                "surfaceLinks": [],
                "cellID": -1
            },
            {
                "textTokens": [],
                "isNumeric": false,
                "tdHtmlString": "<td colspan=\"1\" rowspan=\"1\"> </td>",
                "text": "",
                "subtableID": -1,
                "surfaceLinks": [],
                "cellID": -1
            },
            {
                "textTokens": [],
                "isNumeric": false,
                "tdHtmlString": "<td colspan=\"1\" rowspan=\"1\"> </td>",
                "text": "",
                "subtableID": -1,
                "surfaceLinks": [],
                "cellID": -1
            },
            {
                "textTokens": [],
                "isNumeric": false,
                "tdHtmlString": "<td colspan=\"1\" rowspan=\"1\"> </td>",
                "text": "",
                "subtableID": -1,
                "surfaceLinks": [],
                "cellID": -1
            },
            {
                "textTokens": [],
                "isNumeric": false,
                "tdHtmlString": "<td colspan=\"1\" rowspan=\"1\"> Named by Case in 1921, in the 1980s it was referred to Arganodus. </td>",
                "text": "Named by Case in 1921, in the 1980s it was referred to Arganodus.",
                "subtableID": -1,
                "surfaceLinks": [],
                "cellID": -1
            },
            {
                "textTokens": [],
                "isNumeric": false,
                "tdHtmlString": "",
                "text": "",
                "subtableID": -1,
                "surfaceLinks": [],
                "cellID": -1
            }
        ]
    ],
    "order": 0.323408002499491,
    "numHeaderRows": 2,
    "numCols": 7
}