{
    "sectionTitle": "Results",
    "pgId": 33454033,
    "numDataRows": 13,
    "_id": "33454033-1",
    "pgTitle": "Athletics at the 2002 Commonwealth Games – Women's discus throw",
    "numericColumns": [
        0,
        3,
        4,
        5,
        9
    ],
    "tableCaption": "Results",
    "tableHeaders": [
        [
            {
                "textTokens": [],
                "isNumeric": false,
                "tdHtmlString": "<th colspan=\"1\" rowspan=\"1\"> Rank </th>",
                "text": "Rank",
                "subtableID": -1,
                "surfaceLinks": [],
                "cellID": -1
            },
            {
                "textTokens": [],
                "isNumeric": false,
                "tdHtmlString": "<th colspan=\"1\" rowspan=\"1\"> Athlete </th>",
                "text": "Athlete",
                "subtableID": -1,
                "surfaceLinks": [],
                "cellID": -1
            },
            {
                "textTokens": [],
                "isNumeric": false,
                "tdHtmlString": "<th colspan=\"1\" rowspan=\"1\"> Nationality </th>",
                "text": "Nationality",
                "subtableID": -1,
                "surfaceLinks": [],
                "cellID": -1
            },
            {
                "textTokens": [],
                "isNumeric": false,
                "tdHtmlString": "<th colspan=\"1\" rowspan=\"1\"> #1 </th>",
                "text": "#1",
                "subtableID": -1,
                "surfaceLinks": [],
                "cellID": -1
            },
            {
                "textTokens": [],
                "isNumeric": false,
                "tdHtmlString": "<th colspan=\"1\" rowspan=\"1\"> #2 </th>",
                "text": "#2",
                "subtableID": -1,
                "surfaceLinks": [],
                "cellID": -1
            },
            {
                "textTokens": [],
                "isNumeric": false,
                "tdHtmlString": "<th colspan=\"1\" rowspan=\"1\"> #3 </th>",
                "text": "#3",
                "subtableID": -1,
                "surfaceLinks": [],
                "cellID": -1
            },
            {
                "textTokens": [],
                "isNumeric": false,
                "tdHtmlString": "<th colspan=\"1\" rowspan=\"1\"> #4 </th>",
                "text": "#4",
                "subtableID": -1,
                "surfaceLinks": [],
                "cellID": -1
            },
            {
                "textTokens": [],
                "isNumeric": false,
                "tdHtmlString": "<th colspan=\"1\" rowspan=\"1\"> #5 </th>",
                "text": "#5",
                "subtableID": -1,
                "surfaceLinks": [],
                "cellID": -1
            },
            {
                "textTokens": [],
                "isNumeric": false,
                "tdHtmlString": "<th colspan=\"1\" rowspan=\"1\"> #6 </th>",
                "text": "#6",
                "subtableID": -1,
                "surfaceLinks": [],
                "cellID": -1
            },
            {
                "textTokens": [],
                "isNumeric": false,
                "tdHtmlString": "<th colspan=\"1\" rowspan=\"1\"> Result </th>",
                "text": "Result",
                "subtableID": -1,
                "surfaceLinks": [],
                "cellID": -1
            },
            {
                "textTokens": [],
                "isNumeric": false,
                "tdHtmlString": "<th colspan=\"1\" rowspan=\"1\"> Notes </th>",
                "text": "Notes",
                "subtableID": -1,
                "surfaceLinks": [],
                "cellID": -1
            }
        ]
    ],
    "tableId": 1,
    "tableData": [
        [
            {
                "textTokens": [],
                "isNumeric": false,
                "tdHtmlString": "<td colspan=\"1\" rowspan=\"1\">  <span> </span> </td>",
                "text": "",
                "subtableID": -1,
                "surfaceLinks": [],
                "cellID": -1
            },
            {
                "textTokens": [],
                "isNumeric": false,
                "tdHtmlString": "<td colspan=\"1\" rowspan=\"1\"> <a href=\"http://www.wikipedia.org/wiki/Beatrice_Faumuina\" shape=\"rect\">Beatrice Faumuina</a> </td>",
                "text": "Beatrice Faumuina",
                "subtableID": -1,
                "surfaceLinks": [
                    {
                        "offset": 0,
                        "target": {
                            "language": "en",
                            "redirecting": false,
                            "id": 939260,
                            "title": "Beatrice_Faumuina",
                            "namesapce": 0
                        },
                        "isInTemplate": false,
                        "locType": "MAIN_TABLE",
                        "surface": "Beatrice Faumuina",
                        "inTemplate": false,
                        "endOffset": 17,
                        "linkType": "INTERNAL"
                    }
                ],
                "cellID": -1
            },
            {
                "textTokens": [],
                "isNumeric": false,
                "tdHtmlString": "<td colspan=\"1\" rowspan=\"1\"> <span>  </span> <a href=\"http://www.wikipedia.org/wiki/New_Zealand\" shape=\"rect\">New Zealand</a> </td>",
                "text": "New Zealand",
                "subtableID": -1,
                "surfaceLinks": [
                    {
                        "offset": 0,
                        "target": {
                            "language": "en",
                            "redirecting": false,
                            "id": 4913064,
                            "title": "New_Zealand",
                            "namesapce": 0
                        },
                        "isInTemplate": false,
                        "locType": "MAIN_TABLE",
                        "surface": "New Zealand",
                        "inTemplate": false,
                        "endOffset": 11,
                        "linkType": "INTERNAL"
                    }
                ],
                "cellID": -1
            },
            {
                "textTokens": [],
                "isNumeric": true,
                "tdHtmlString": "<td colspan=\"1\" rowspan=\"1\"> 58.24 </td>",
                "text": "58.24",
                "subtableID": -1,
                "surfaceLinks": [],
                "cellID": -1
            },
            {
                "textTokens": [],
                "isNumeric": true,
                "tdHtmlString": "<td colspan=\"1\" rowspan=\"1\"> 60.83 </td>",
                "text": "60.83",
                "subtableID": -1,
                "surfaceLinks": [],
                "cellID": -1
            },
            {
                "textTokens": [],
                "isNumeric": false,
                "tdHtmlString": "<td colspan=\"1\" rowspan=\"1\"> x </td>",
                "text": "x",
                "subtableID": -1,
                "surfaceLinks": [],
                "cellID": -1
            },
            {
                "textTokens": [],
                "isNumeric": false,
                "tdHtmlString": "<td colspan=\"1\" rowspan=\"1\"> x </td>",
                "text": "x",
                "subtableID": -1,
                "surfaceLinks": [],
                "cellID": -1
            },
            {
                "textTokens": [],
                "isNumeric": true,
                "tdHtmlString": "<td colspan=\"1\" rowspan=\"1\"> 60.50 </td>",
                "text": "60.50",
                "subtableID": -1,
                "surfaceLinks": [],
                "cellID": -1
            },
            {
                "textTokens": [],
                "isNumeric": false,
                "tdHtmlString": "<td colspan=\"1\" rowspan=\"1\"> x </td>",
                "text": "x",
                "subtableID": -1,
                "surfaceLinks": [],
                "cellID": -1
            },
            {
                "textTokens": [],
                "isNumeric": true,
                "tdHtmlString": "<td colspan=\"1\" rowspan=\"1\"> 60.83 </td>",
                "text": "60.83",
                "subtableID": -1,
                "surfaceLinks": [],
                "cellID": -1
            },
            {
                "textTokens": [],
                "isNumeric": false,
                "tdHtmlString": "<td colspan=\"1\" rowspan=\"1\"> </td>",
                "text": "",
                "subtableID": -1,
                "surfaceLinks": [],
                "cellID": -1
            }
        ],
        [
            {
                "textTokens": [],
                "isNumeric": false,
                "tdHtmlString": "<td colspan=\"1\" rowspan=\"1\">  <span> </span> </td>",
                "text": "",
                "subtableID": -1,
                "surfaceLinks": [],
                "cellID": -1
            },
            {
                "textTokens": [],
                "isNumeric": false,
                "tdHtmlString": "<td colspan=\"1\" rowspan=\"1\"> <a href=\"http://www.wikipedia.org/wiki/Neelam_Jaswant_Singh\" shape=\"rect\">Neelam Jaswant Singh</a> </td>",
                "text": "Neelam Jaswant Singh",
                "subtableID": -1,
                "surfaceLinks": [
                    {
                        "offset": 0,
                        "target": {
                            "language": "en",
                            "redirecting": false,
                            "id": 8659169,
                            "title": "Neelam_Jaswant_Singh",
                            "namesapce": 0
                        },
                        "isInTemplate": false,
                        "locType": "MAIN_TABLE",
                        "surface": "Neelam Jaswant Singh",
                        "inTemplate": false,
                        "endOffset": 20,
                        "linkType": "INTERNAL"
                    }
                ],
                "cellID": -1
            },
            {
                "textTokens": [],
                "isNumeric": false,
                "tdHtmlString": "<td colspan=\"1\" rowspan=\"1\"> <span>  </span> <a href=\"http://www.wikipedia.org/wiki/India\" shape=\"rect\">India</a> </td>",
                "text": "India",
                "subtableID": -1,
                "surfaceLinks": [
                    {
                        "offset": 0,
                        "target": {
                            "language": "en",
                            "redirecting": false,
                            "id": 14533,
                            "title": "India",
                            "namesapce": 0
                        },
                        "isInTemplate": false,
                        "locType": "MAIN_TABLE",
                        "surface": "India",
                        "inTemplate": false,
                        "endOffset": 5,
                        "linkType": "INTERNAL"
                    }
                ],
                "cellID": -1
            },
            {
                "textTokens": [],
                "isNumeric": true,
                "tdHtmlString": "<td colspan=\"1\" rowspan=\"1\"> 54.85 </td>",
                "text": "54.85",
                "subtableID": -1,
                "surfaceLinks": [],
                "cellID": -1
            },
            {
                "textTokens": [],
                "isNumeric": true,
                "tdHtmlString": "<td colspan=\"1\" rowspan=\"1\"> 56.04 </td>",
                "text": "56.04",
                "subtableID": -1,
                "surfaceLinks": [],
                "cellID": -1
            },
            {
                "textTokens": [],
                "isNumeric": true,
                "tdHtmlString": "<td colspan=\"1\" rowspan=\"1\"> 56.91 </td>",
                "text": "56.91",
                "subtableID": -1,
                "surfaceLinks": [],
                "cellID": -1
            },
            {
                "textTokens": [],
                "isNumeric": true,
                "tdHtmlString": "<td colspan=\"1\" rowspan=\"1\"> 53.18 </td>",
                "text": "53.18",
                "subtableID": -1,
                "surfaceLinks": [],
                "cellID": -1
            },
            {
                "textTokens": [],
                "isNumeric": true,
                "tdHtmlString": "<td colspan=\"1\" rowspan=\"1\"> 58.49 </td>",
                "text": "58.49",
                "subtableID": -1,
                "surfaceLinks": [],
                "cellID": -1
            },
            {
                "textTokens": [],
                "isNumeric": true,
                "tdHtmlString": "<td colspan=\"1\" rowspan=\"1\"> 54.75 </td>",
                "text": "54.75",
                "subtableID": -1,
                "surfaceLinks": [],
                "cellID": -1
            },
            {
                "textTokens": [],
                "isNumeric": true,
                "tdHtmlString": "<td colspan=\"1\" rowspan=\"1\"> 58.49 </td>",
                "text": "58.49",
                "subtableID": -1,
                "surfaceLinks": [],
                "cellID": -1
            },
            {
                "textTokens": [],
                "isNumeric": false,
                "tdHtmlString": "<td colspan=\"1\" rowspan=\"1\"> </td>",
                "text": "",
                "subtableID": -1,
                "surfaceLinks": [],
                "cellID": -1
            }
        ],
        [
            {
                "textTokens": [],
                "isNumeric": false,
                "tdHtmlString": "<td colspan=\"1\" rowspan=\"1\">  <span> </span> </td>",
                "text": "",
                "subtableID": -1,
                "surfaceLinks": [],
                "cellID": -1
            },
            {
                "textTokens": [],
                "isNumeric": false,
                "tdHtmlString": "<td colspan=\"1\" rowspan=\"1\"> <a href=\"http://www.wikipedia.org/wiki/Shelley_Newman\" shape=\"rect\">Shelley Newman</a> </td>",
                "text": "Shelley Newman",
                "subtableID": -1,
                "surfaceLinks": [
                    {
                        "offset": 0,
                        "target": {
                            "language": "en",
                            "redirecting": false,
                            "id": 12292787,
                            "title": "Shelley_Newman",
                            "namesapce": 0
                        },
                        "isInTemplate": false,
                        "locType": "MAIN_TABLE",
                        "surface": "Shelley Newman",
                        "inTemplate": false,
                        "endOffset": 14,
                        "linkType": "INTERNAL"
                    }
                ],
                "cellID": -1
            },
            {
                "textTokens": [],
                "isNumeric": false,
                "tdHtmlString": "<td colspan=\"1\" rowspan=\"1\"> <span>  </span> <a href=\"http://www.wikipedia.org/wiki/England\" shape=\"rect\">England</a> </td>",
                "text": "England",
                "subtableID": -1,
                "surfaceLinks": [
                    {
                        "offset": 0,
                        "target": {
                            "language": "en",
                            "redirecting": false,
                            "id": 9316,
                            "title": "England",
                            "namesapce": 0
                        },
                        "isInTemplate": false,
                        "locType": "MAIN_TABLE",
                        "surface": "England",
                        "inTemplate": false,
                        "endOffset": 7,
                        "linkType": "INTERNAL"
                    }
                ],
                "cellID": -1
            },
            {
                "textTokens": [],
                "isNumeric": true,
                "tdHtmlString": "<td colspan=\"1\" rowspan=\"1\"> 56.72 </td>",
                "text": "56.72",
                "subtableID": -1,
                "surfaceLinks": [],
                "cellID": -1
            },
            {
                "textTokens": [],
                "isNumeric": true,
                "tdHtmlString": "<td colspan=\"1\" rowspan=\"1\"> 56.64 </td>",
                "text": "56.64",
                "subtableID": -1,
                "surfaceLinks": [],
                "cellID": -1
            },
            {
                "textTokens": [],
                "isNumeric": true,
                "tdHtmlString": "<td colspan=\"1\" rowspan=\"1\"> 58.13 </td>",
                "text": "58.13",
                "subtableID": -1,
                "surfaceLinks": [],
                "cellID": -1
            },
            {
                "textTokens": [],
                "isNumeric": true,
                "tdHtmlString": "<td colspan=\"1\" rowspan=\"1\"> 57.25 </td>",
                "text": "57.25",
                "subtableID": -1,
                "surfaceLinks": [],
                "cellID": -1
            },
            {
                "textTokens": [],
                "isNumeric": false,
                "tdHtmlString": "<td colspan=\"1\" rowspan=\"1\"> x </td>",
                "text": "x",
                "subtableID": -1,
                "surfaceLinks": [],
                "cellID": -1
            },
            {
                "textTokens": [],
                "isNumeric": true,
                "tdHtmlString": "<td colspan=\"1\" rowspan=\"1\"> 57.92 </td>",
                "text": "57.92",
                "subtableID": -1,
                "surfaceLinks": [],
                "cellID": -1
            },
            {
                "textTokens": [],
                "isNumeric": true,
                "tdHtmlString": "<td colspan=\"1\" rowspan=\"1\"> 58.13 </td>",
                "text": "58.13",
                "subtableID": -1,
                "surfaceLinks": [],
                "cellID": -1
            },
            {
                "textTokens": [],
                "isNumeric": false,
                "tdHtmlString": "<td colspan=\"1\" rowspan=\"1\"> </td>",
                "text": "",
                "subtableID": -1,
                "surfaceLinks": [],
                "cellID": -1
            }
        ],
        [
            {
                "textTokens": [],
                "isNumeric": true,
                "tdHtmlString": "<td colspan=\"1\" rowspan=\"1\">  <span> 4</span> </td>",
                "text": "4",
                "subtableID": -1,
                "surfaceLinks": [],
                "cellID": -1
            },
            {
                "textTokens": [],
                "isNumeric": false,
                "tdHtmlString": "<td colspan=\"1\" rowspan=\"1\"> <a href=\"http://www.wikipedia.org/wiki/Philippa_Roles\" shape=\"rect\">Philippa Roles</a> </td>",
                "text": "Philippa Roles",
                "subtableID": -1,
                "surfaceLinks": [
                    {
                        "offset": 0,
                        "target": {
                            "language": "en",
                            "redirecting": false,
                            "id": 12292732,
                            "title": "Philippa_Roles",
                            "namesapce": 0
                        },
                        "isInTemplate": false,
                        "locType": "MAIN_TABLE",
                        "surface": "Philippa Roles",
                        "inTemplate": false,
                        "endOffset": 14,
                        "linkType": "INTERNAL"
                    }
                ],
                "cellID": -1
            },
            {
                "textTokens": [],
                "isNumeric": false,
                "tdHtmlString": "<td colspan=\"1\" rowspan=\"1\"> <span>  </span> <a href=\"http://www.wikipedia.org/wiki/Wales\" shape=\"rect\">Wales</a> </td>",
                "text": "Wales",
                "subtableID": -1,
                "surfaceLinks": [
                    {
                        "offset": 0,
                        "target": {
                            "language": "en",
                            "redirecting": false,
                            "id": 69894,
                            "title": "Wales",
                            "namesapce": 0
                        },
                        "isInTemplate": false,
                        "locType": "MAIN_TABLE",
                        "surface": "Wales",
                        "inTemplate": false,
                        "endOffset": 5,
                        "linkType": "INTERNAL"
                    }
                ],
                "cellID": -1
            },
            {
                "textTokens": [],
                "isNumeric": true,
                "tdHtmlString": "<td colspan=\"1\" rowspan=\"1\"> 53.91 </td>",
                "text": "53.91",
                "subtableID": -1,
                "surfaceLinks": [],
                "cellID": -1
            },
            {
                "textTokens": [],
                "isNumeric": true,
                "tdHtmlString": "<td colspan=\"1\" rowspan=\"1\"> 56.39 </td>",
                "text": "56.39",
                "subtableID": -1,
                "surfaceLinks": [],
                "cellID": -1
            },
            {
                "textTokens": [],
                "isNumeric": true,
                "tdHtmlString": "<td colspan=\"1\" rowspan=\"1\"> 56.92 </td>",
                "text": "56.92",
                "subtableID": -1,
                "surfaceLinks": [],
                "cellID": -1
            },
            {
                "textTokens": [],
                "isNumeric": true,
                "tdHtmlString": "<td colspan=\"1\" rowspan=\"1\"> 56.50 </td>",
                "text": "56.50",
                "subtableID": -1,
                "surfaceLinks": [],
                "cellID": -1
            },
            {
                "textTokens": [],
                "isNumeric": true,
                "tdHtmlString": "<td colspan=\"1\" rowspan=\"1\"> 56.66 </td>",
                "text": "56.66",
                "subtableID": -1,
                "surfaceLinks": [],
                "cellID": -1
            },
            {
                "textTokens": [],
                "isNumeric": true,
                "tdHtmlString": "<td colspan=\"1\" rowspan=\"1\"> 57.65 </td>",
                "text": "57.65",
                "subtableID": -1,
                "surfaceLinks": [],
                "cellID": -1
            },
            {
                "textTokens": [],
                "isNumeric": true,
                "tdHtmlString": "<td colspan=\"1\" rowspan=\"1\"> 57.65 </td>",
                "text": "57.65",
                "subtableID": -1,
                "surfaceLinks": [],
                "cellID": -1
            },
            {
                "textTokens": [],
                "isNumeric": false,
                "tdHtmlString": "<td colspan=\"1\" rowspan=\"1\"> </td>",
                "text": "",
                "subtableID": -1,
                "surfaceLinks": [],
                "cellID": -1
            }
        ],
        [
            {
                "textTokens": [],
                "isNumeric": true,
                "tdHtmlString": "<td colspan=\"1\" rowspan=\"1\">  <span> 5</span> </td>",
                "text": "5",
                "subtableID": -1,
                "surfaceLinks": [],
                "cellID": -1
            },
            {
                "textTokens": [],
                "isNumeric": false,
                "tdHtmlString": "<td colspan=\"1\" rowspan=\"1\"> <a href=\"http://www.wikipedia.org/wiki/Alison_Lever\" shape=\"rect\">Alison Lever</a> </td>",
                "text": "Alison Lever",
                "subtableID": -1,
                "surfaceLinks": [
                    {
                        "offset": 0,
                        "target": {
                            "language": "en",
                            "redirecting": false,
                            "id": -1,
                            "title": "Alison_Lever",
                            "namesapce": 0
                        },
                        "isInTemplate": false,
                        "locType": "MAIN_TABLE",
                        "surface": "Alison Lever",
                        "inTemplate": false,
                        "endOffset": 12,
                        "linkType": "INTERNAL_RED"
                    }
                ],
                "cellID": -1
            },
            {
                "textTokens": [],
                "isNumeric": false,
                "tdHtmlString": "<td colspan=\"1\" rowspan=\"1\"> <span>  </span> <a href=\"http://www.wikipedia.org/wiki/Australia\" shape=\"rect\">Australia</a> </td>",
                "text": "Australia",
                "subtableID": -1,
                "surfaceLinks": [
                    {
                        "offset": 0,
                        "target": {
                            "language": "en",
                            "redirecting": false,
                            "id": 4689264,
                            "title": "Australia",
                            "namesapce": 0
                        },
                        "isInTemplate": false,
                        "locType": "MAIN_TABLE",
                        "surface": "Australia",
                        "inTemplate": false,
                        "endOffset": 9,
                        "linkType": "INTERNAL"
                    }
                ],
                "cellID": -1
            },
            {
                "textTokens": [],
                "isNumeric": true,
                "tdHtmlString": "<td colspan=\"1\" rowspan=\"1\"> 57.25 </td>",
                "text": "57.25",
                "subtableID": -1,
                "surfaceLinks": [],
                "cellID": -1
            },
            {
                "textTokens": [],
                "isNumeric": true,
                "tdHtmlString": "<td colspan=\"1\" rowspan=\"1\"> 55.78 </td>",
                "text": "55.78",
                "subtableID": -1,
                "surfaceLinks": [],
                "cellID": -1
            },
            {
                "textTokens": [],
                "isNumeric": true,
                "tdHtmlString": "<td colspan=\"1\" rowspan=\"1\"> 56.38 </td>",
                "text": "56.38",
                "subtableID": -1,
                "surfaceLinks": [],
                "cellID": -1
            },
            {
                "textTokens": [],
                "isNumeric": true,
                "tdHtmlString": "<td colspan=\"1\" rowspan=\"1\"> 55.39 </td>",
                "text": "55.39",
                "subtableID": -1,
                "surfaceLinks": [],
                "cellID": -1
            },
            {
                "textTokens": [],
                "isNumeric": true,
                "tdHtmlString": "<td colspan=\"1\" rowspan=\"1\"> 57.13 </td>",
                "text": "57.13",
                "subtableID": -1,
                "surfaceLinks": [],
                "cellID": -1
            },
            {
                "textTokens": [],
                "isNumeric": false,
                "tdHtmlString": "<td colspan=\"1\" rowspan=\"1\"> x </td>",
                "text": "x",
                "subtableID": -1,
                "surfaceLinks": [],
                "cellID": -1
            },
            {
                "textTokens": [],
                "isNumeric": true,
                "tdHtmlString": "<td colspan=\"1\" rowspan=\"1\"> 57.25 </td>",
                "text": "57.25",
                "subtableID": -1,
                "surfaceLinks": [],
                "cellID": -1
            },
            {
                "textTokens": [],
                "isNumeric": false,
                "tdHtmlString": "<td colspan=\"1\" rowspan=\"1\"> </td>",
                "text": "",
                "subtableID": -1,
                "surfaceLinks": [],
                "cellID": -1
            }
        ],
        [
            {
                "textTokens": [],
                "isNumeric": true,
                "tdHtmlString": "<td colspan=\"1\" rowspan=\"1\">  <span> 6</span> </td>",
                "text": "6",
                "subtableID": -1,
                "surfaceLinks": [],
                "cellID": -1
            },
            {
                "textTokens": [],
                "isNumeric": false,
                "tdHtmlString": "<td colspan=\"1\" rowspan=\"1\"> <a href=\"http://www.wikipedia.org/wiki/Elizna_Naudé\" shape=\"rect\">Elizna Naudé</a> </td>",
                "text": "Elizna Naudé",
                "subtableID": -1,
                "surfaceLinks": [
                    {
                        "offset": 0,
                        "target": {
                            "language": "en",
                            "redirecting": false,
                            "id": 10103171,
                            "title": "Elizna_Naudé",
                            "namesapce": 0
                        },
                        "isInTemplate": false,
                        "locType": "MAIN_TABLE",
                        "surface": "Elizna Naudé",
                        "inTemplate": false,
                        "endOffset": 12,
                        "linkType": "INTERNAL"
                    }
                ],
                "cellID": -1
            },
            {
                "textTokens": [],
                "isNumeric": false,
                "tdHtmlString": "<td colspan=\"1\" rowspan=\"1\"> <span>  </span> <a href=\"http://www.wikipedia.org/wiki/South_Africa\" shape=\"rect\">South Africa</a> </td>",
                "text": "South Africa",
                "subtableID": -1,
                "surfaceLinks": [
                    {
                        "offset": 0,
                        "target": {
                            "language": "en",
                            "redirecting": false,
                            "id": 17416221,
                            "title": "South_Africa",
                            "namesapce": 0
                        },
                        "isInTemplate": false,
                        "locType": "MAIN_TABLE",
                        "surface": "South Africa",
                        "inTemplate": false,
                        "endOffset": 12,
                        "linkType": "INTERNAL"
                    }
                ],
                "cellID": -1
            },
            {
                "textTokens": [],
                "isNumeric": true,
                "tdHtmlString": "<td colspan=\"1\" rowspan=\"1\"> 55.41 </td>",
                "text": "55.41",
                "subtableID": -1,
                "surfaceLinks": [],
                "cellID": -1
            },
            {
                "textTokens": [],
                "isNumeric": true,
                "tdHtmlString": "<td colspan=\"1\" rowspan=\"1\"> 51.82 </td>",
                "text": "51.82",
                "subtableID": -1,
                "surfaceLinks": [],
                "cellID": -1
            },
            {
                "textTokens": [],
                "isNumeric": true,
                "tdHtmlString": "<td colspan=\"1\" rowspan=\"1\"> 53.03 </td>",
                "text": "53.03",
                "subtableID": -1,
                "surfaceLinks": [],
                "cellID": -1
            },
            {
                "textTokens": [],
                "isNumeric": true,
                "tdHtmlString": "<td colspan=\"1\" rowspan=\"1\"> 52.95 </td>",
                "text": "52.95",
                "subtableID": -1,
                "surfaceLinks": [],
                "cellID": -1
            },
            {
                "textTokens": [],
                "isNumeric": false,
                "tdHtmlString": "<td colspan=\"1\" rowspan=\"1\"> x </td>",
                "text": "x",
                "subtableID": -1,
                "surfaceLinks": [],
                "cellID": -1
            },
            {
                "textTokens": [],
                "isNumeric": true,
                "tdHtmlString": "<td colspan=\"1\" rowspan=\"1\"> 54.92 </td>",
                "text": "54.92",
                "subtableID": -1,
                "surfaceLinks": [],
                "cellID": -1
            },
            {
                "textTokens": [],
                "isNumeric": true,
                "tdHtmlString": "<td colspan=\"1\" rowspan=\"1\"> 55.41 </td>",
                "text": "55.41",
                "subtableID": -1,
                "surfaceLinks": [],
                "cellID": -1
            },
            {
                "textTokens": [],
                "isNumeric": false,
                "tdHtmlString": "<td colspan=\"1\" rowspan=\"1\"> </td>",
                "text": "",
                "subtableID": -1,
                "surfaceLinks": [],
                "cellID": -1
            }
        ],
        [
            {
                "textTokens": [],
                "isNumeric": true,
                "tdHtmlString": "<td colspan=\"1\" rowspan=\"1\">  <span> 7</span> </td>",
                "text": "7",
                "subtableID": -1,
                "surfaceLinks": [],
                "cellID": -1
            },
            {
                "textTokens": [],
                "isNumeric": false,
                "tdHtmlString": "<td colspan=\"1\" rowspan=\"1\"> <a href=\"http://www.wikipedia.org/wiki/Claire_Smithson\" shape=\"rect\">Claire Smithson</a> </td>",
                "text": "Claire Smithson",
                "subtableID": -1,
                "surfaceLinks": [
                    {
                        "offset": 0,
                        "target": {
                            "language": "en",
                            "redirecting": false,
                            "id": -1,
                            "title": "Claire_Smithson",
                            "namesapce": 0
                        },
                        "isInTemplate": false,
                        "locType": "MAIN_TABLE",
                        "surface": "Claire Smithson",
                        "inTemplate": false,
                        "endOffset": 15,
                        "linkType": "INTERNAL_RED"
                    }
                ],
                "cellID": -1
            },
            {
                "textTokens": [],
                "isNumeric": false,
                "tdHtmlString": "<td colspan=\"1\" rowspan=\"1\"> <span>  </span> <a href=\"http://www.wikipedia.org/wiki/England\" shape=\"rect\">England</a> </td>",
                "text": "England",
                "subtableID": -1,
                "surfaceLinks": [
                    {
                        "offset": 0,
                        "target": {
                            "language": "en",
                            "redirecting": false,
                            "id": 9316,
                            "title": "England",
                            "namesapce": 0
                        },
                        "isInTemplate": false,
                        "locType": "MAIN_TABLE",
                        "surface": "England",
                        "inTemplate": false,
                        "endOffset": 7,
                        "linkType": "INTERNAL"
                    }
                ],
                "cellID": -1
            },
            {
                "textTokens": [],
                "isNumeric": false,
                "tdHtmlString": "<td colspan=\"1\" rowspan=\"1\"> x </td>",
                "text": "x",
                "subtableID": -1,
                "surfaceLinks": [],
                "cellID": -1
            },
            {
                "textTokens": [],
                "isNumeric": true,
                "tdHtmlString": "<td colspan=\"1\" rowspan=\"1\"> 55.03 </td>",
                "text": "55.03",
                "subtableID": -1,
                "surfaceLinks": [],
                "cellID": -1
            },
            {
                "textTokens": [],
                "isNumeric": true,
                "tdHtmlString": "<td colspan=\"1\" rowspan=\"1\"> 52.84 </td>",
                "text": "52.84",
                "subtableID": -1,
                "surfaceLinks": [],
                "cellID": -1
            },
            {
                "textTokens": [],
                "isNumeric": false,
                "tdHtmlString": "<td colspan=\"1\" rowspan=\"1\"> x </td>",
                "text": "x",
                "subtableID": -1,
                "surfaceLinks": [],
                "cellID": -1
            },
            {
                "textTokens": [],
                "isNumeric": false,
                "tdHtmlString": "<td colspan=\"1\" rowspan=\"1\"> x </td>",
                "text": "x",
                "subtableID": -1,
                "surfaceLinks": [],
                "cellID": -1
            },
            {
                "textTokens": [],
                "isNumeric": false,
                "tdHtmlString": "<td colspan=\"1\" rowspan=\"1\"> x </td>",
                "text": "x",
                "subtableID": -1,
                "surfaceLinks": [],
                "cellID": -1
            },
            {
                "textTokens": [],
                "isNumeric": true,
                "tdHtmlString": "<td colspan=\"1\" rowspan=\"1\"> 55.03 </td>",
                "text": "55.03",
                "subtableID": -1,
                "surfaceLinks": [],
                "cellID": -1
            },
            {
                "textTokens": [],
                "isNumeric": false,
                "tdHtmlString": "<td colspan=\"1\" rowspan=\"1\"> PB </td>",
                "text": "PB",
                "subtableID": -1,
                "surfaceLinks": [],
                "cellID": -1
            }
        ],
        [
            {
                "textTokens": [],
                "isNumeric": true,
                "tdHtmlString": "<td colspan=\"1\" rowspan=\"1\">  <span> 8</span> </td>",
                "text": "8",
                "subtableID": -1,
                "surfaceLinks": [],
                "cellID": -1
            },
            {
                "textTokens": [],
                "isNumeric": false,
                "tdHtmlString": "<td colspan=\"1\" rowspan=\"1\"> <a href=\"http://www.wikipedia.org/wiki/Monique_Nacsa\" shape=\"rect\">Monique Nacsa</a> </td>",
                "text": "Monique Nacsa",
                "subtableID": -1,
                "surfaceLinks": [
                    {
                        "offset": 0,
                        "target": {
                            "language": "en",
                            "redirecting": false,
                            "id": -1,
                            "title": "Monique_Nacsa",
                            "namesapce": 0
                        },
                        "isInTemplate": false,
                        "locType": "MAIN_TABLE",
                        "surface": "Monique Nacsa",
                        "inTemplate": false,
                        "endOffset": 13,
                        "linkType": "INTERNAL_RED"
                    }
                ],
                "cellID": -1
            },
            {
                "textTokens": [],
                "isNumeric": false,
                "tdHtmlString": "<td colspan=\"1\" rowspan=\"1\"> <span>  </span> <a href=\"http://www.wikipedia.org/wiki/Australia\" shape=\"rect\">Australia</a> </td>",
                "text": "Australia",
                "subtableID": -1,
                "surfaceLinks": [
                    {
                        "offset": 0,
                        "target": {
                            "language": "en",
                            "redirecting": false,
                            "id": 4689264,
                            "title": "Australia",
                            "namesapce": 0
                        },
                        "isInTemplate": false,
                        "locType": "MAIN_TABLE",
                        "surface": "Australia",
                        "inTemplate": false,
                        "endOffset": 9,
                        "linkType": "INTERNAL"
                    }
                ],
                "cellID": -1
            },
            {
                "textTokens": [],
                "isNumeric": true,
                "tdHtmlString": "<td colspan=\"1\" rowspan=\"1\"> 51.57 </td>",
                "text": "51.57",
                "subtableID": -1,
                "surfaceLinks": [],
                "cellID": -1
            },
            {
                "textTokens": [],
                "isNumeric": true,
                "tdHtmlString": "<td colspan=\"1\" rowspan=\"1\"> 53.34 </td>",
                "text": "53.34",
                "subtableID": -1,
                "surfaceLinks": [],
                "cellID": -1
            },
            {
                "textTokens": [],
                "isNumeric": true,
                "tdHtmlString": "<td colspan=\"1\" rowspan=\"1\"> 54.46 </td>",
                "text": "54.46",
                "subtableID": -1,
                "surfaceLinks": [],
                "cellID": -1
            },
            {
                "textTokens": [],
                "isNumeric": true,
                "tdHtmlString": "<td colspan=\"1\" rowspan=\"1\"> 51.61 </td>",
                "text": "51.61",
                "subtableID": -1,
                "surfaceLinks": [],
                "cellID": -1
            },
            {
                "textTokens": [],
                "isNumeric": true,
                "tdHtmlString": "<td colspan=\"1\" rowspan=\"1\"> 54.45 </td>",
                "text": "54.45",
                "subtableID": -1,
                "surfaceLinks": [],
                "cellID": -1
            },
            {
                "textTokens": [],
                "isNumeric": true,
                "tdHtmlString": "<td colspan=\"1\" rowspan=\"1\"> 52.73 </td>",
                "text": "52.73",
                "subtableID": -1,
                "surfaceLinks": [],
                "cellID": -1
            },
            {
                "textTokens": [],
                "isNumeric": true,
                "tdHtmlString": "<td colspan=\"1\" rowspan=\"1\"> 54.46 </td>",
                "text": "54.46",
                "subtableID": -1,
                "surfaceLinks": [],
                "cellID": -1
            },
            {
                "textTokens": [],
                "isNumeric": false,
                "tdHtmlString": "<td colspan=\"1\" rowspan=\"1\"> </td>",
                "text": "",
                "subtableID": -1,
                "surfaceLinks": [],
                "cellID": -1
            }
        ],
        [
            {
                "textTokens": [],
                "isNumeric": true,
                "tdHtmlString": "<td colspan=\"1\" rowspan=\"1\">  <span> 9</span> </td>",
                "text": "9",
                "subtableID": -1,
                "surfaceLinks": [],
                "cellID": -1
            },
            {
                "textTokens": [],
                "isNumeric": false,
                "tdHtmlString": "<td colspan=\"1\" rowspan=\"1\"> <a href=\"http://www.wikipedia.org/wiki/Vivian_Chukwuemeka\" shape=\"rect\">Vivian Chukwuemeka</a> </td>",
                "text": "Vivian Chukwuemeka",
                "subtableID": -1,
                "surfaceLinks": [
                    {
                        "offset": 0,
                        "target": {
                            "language": "en",
                            "redirecting": false,
                            "id": 4511688,
                            "title": "Vivian_Chukwuemeka",
                            "namesapce": 0
                        },
                        "isInTemplate": false,
                        "locType": "MAIN_TABLE",
                        "surface": "Vivian Chukwuemeka",
                        "inTemplate": false,
                        "endOffset": 18,
                        "linkType": "INTERNAL"
                    }
                ],
                "cellID": -1
            },
            {
                "textTokens": [],
                "isNumeric": false,
                "tdHtmlString": "<td colspan=\"1\" rowspan=\"1\"> <span>  </span> <a href=\"http://www.wikipedia.org/wiki/Nigeria\" shape=\"rect\">Nigeria</a> </td>",
                "text": "Nigeria",
                "subtableID": -1,
                "surfaceLinks": [
                    {
                        "offset": 0,
                        "target": {
                            "language": "en",
                            "redirecting": false,
                            "id": 21383,
                            "title": "Nigeria",
                            "namesapce": 0
                        },
                        "isInTemplate": false,
                        "locType": "MAIN_TABLE",
                        "surface": "Nigeria",
                        "inTemplate": false,
                        "endOffset": 7,
                        "linkType": "INTERNAL"
                    }
                ],
                "cellID": -1
            },
            {
                "textTokens": [],
                "isNumeric": true,
                "tdHtmlString": "<td colspan=\"1\" rowspan=\"1\"> 50.06 </td>",
                "text": "50.06",
                "subtableID": -1,
                "surfaceLinks": [],
                "cellID": -1
            },
            {
                "textTokens": [],
                "isNumeric": true,
                "tdHtmlString": "<td colspan=\"1\" rowspan=\"1\"> 53.44 </td>",
                "text": "53.44",
                "subtableID": -1,
                "surfaceLinks": [],
                "cellID": -1
            },
            {
                "textTokens": [],
                "isNumeric": true,
                "tdHtmlString": "<td colspan=\"1\" rowspan=\"1\"> 53.20 </td>",
                "text": "53.20",
                "subtableID": -1,
                "surfaceLinks": [],
                "cellID": -1
            },
            {
                "textTokens": [],
                "isNumeric": false,
                "tdHtmlString": "<td colspan=\"1\" rowspan=\"1\"> </td>",
                "text": "",
                "subtableID": -1,
                "surfaceLinks": [],
                "cellID": -1
            },
            {
                "textTokens": [],
                "isNumeric": false,
                "tdHtmlString": "<td colspan=\"1\" rowspan=\"1\"> </td>",
                "text": "",
                "subtableID": -1,
                "surfaceLinks": [],
                "cellID": -1
            },
            {
                "textTokens": [],
                "isNumeric": false,
                "tdHtmlString": "<td colspan=\"1\" rowspan=\"1\"> </td>",
                "text": "",
                "subtableID": -1,
                "surfaceLinks": [],
                "cellID": -1
            },
            {
                "textTokens": [],
                "isNumeric": true,
                "tdHtmlString": "<td colspan=\"1\" rowspan=\"1\"> 53.44 </td>",
                "text": "53.44",
                "subtableID": -1,
                "surfaceLinks": [],
                "cellID": -1
            },
            {
                "textTokens": [],
                "isNumeric": false,
                "tdHtmlString": "<td colspan=\"1\" rowspan=\"1\"> </td>",
                "text": "",
                "subtableID": -1,
                "surfaceLinks": [],
                "cellID": -1
            }
        ],
        [
            {
                "textTokens": [],
                "isNumeric": true,
                "tdHtmlString": "<td colspan=\"1\" rowspan=\"1\"> 10 </td>",
                "text": "10",
                "subtableID": -1,
                "surfaceLinks": [],
                "cellID": -1
            },
            {
                "textTokens": [],
                "isNumeric": false,
                "tdHtmlString": "<td colspan=\"1\" rowspan=\"1\"> <a href=\"http://www.wikipedia.org/wiki/Jacquie_McKernan\" shape=\"rect\">Jacquie McKernan</a> </td>",
                "text": "Jacquie McKernan",
                "subtableID": -1,
                "surfaceLinks": [
                    {
                        "offset": 0,
                        "target": {
                            "language": "en",
                            "redirecting": false,
                            "id": -1,
                            "title": "Jacquie_McKernan",
                            "namesapce": 0
                        },
                        "isInTemplate": false,
                        "locType": "MAIN_TABLE",
                        "surface": "Jacquie McKernan",
                        "inTemplate": false,
                        "endOffset": 16,
                        "linkType": "INTERNAL_RED"
                    }
                ],
                "cellID": -1
            },
            {
                "textTokens": [],
                "isNumeric": false,
                "tdHtmlString": "<td colspan=\"1\" rowspan=\"1\"> <span>  </span> <a href=\"http://www.wikipedia.org/wiki/Northern_Ireland\" shape=\"rect\">Northern Ireland</a> </td>",
                "text": "Northern Ireland",
                "subtableID": -1,
                "surfaceLinks": [
                    {
                        "offset": 0,
                        "target": {
                            "language": "en",
                            "redirecting": false,
                            "id": 21265,
                            "title": "Northern_Ireland",
                            "namesapce": 0
                        },
                        "isInTemplate": false,
                        "locType": "MAIN_TABLE",
                        "surface": "Northern Ireland",
                        "inTemplate": false,
                        "endOffset": 16,
                        "linkType": "INTERNAL"
                    }
                ],
                "cellID": -1
            },
            {
                "textTokens": [],
                "isNumeric": true,
                "tdHtmlString": "<td colspan=\"1\" rowspan=\"1\"> 50.45 </td>",
                "text": "50.45",
                "subtableID": -1,
                "surfaceLinks": [],
                "cellID": -1
            },
            {
                "textTokens": [],
                "isNumeric": false,
                "tdHtmlString": "<td colspan=\"1\" rowspan=\"1\"> x </td>",
                "text": "x",
                "subtableID": -1,
                "surfaceLinks": [],
                "cellID": -1
            },
            {
                "textTokens": [],
                "isNumeric": false,
                "tdHtmlString": "<td colspan=\"1\" rowspan=\"1\"> x </td>",
                "text": "x",
                "subtableID": -1,
                "surfaceLinks": [],
                "cellID": -1
            },
            {
                "textTokens": [],
                "isNumeric": false,
                "tdHtmlString": "<td colspan=\"1\" rowspan=\"1\"> </td>",
                "text": "",
                "subtableID": -1,
                "surfaceLinks": [],
                "cellID": -1
            },
            {
                "textTokens": [],
                "isNumeric": false,
                "tdHtmlString": "<td colspan=\"1\" rowspan=\"1\"> </td>",
                "text": "",
                "subtableID": -1,
                "surfaceLinks": [],
                "cellID": -1
            },
            {
                "textTokens": [],
                "isNumeric": false,
                "tdHtmlString": "<td colspan=\"1\" rowspan=\"1\"> </td>",
                "text": "",
                "subtableID": -1,
                "surfaceLinks": [],
                "cellID": -1
            },
            {
                "textTokens": [],
                "isNumeric": true,
                "tdHtmlString": "<td colspan=\"1\" rowspan=\"1\"> 50.45 </td>",
                "text": "50.45",
                "subtableID": -1,
                "surfaceLinks": [],
                "cellID": -1
            },
            {
                "textTokens": [],
                "isNumeric": false,
                "tdHtmlString": "<td colspan=\"1\" rowspan=\"1\"> </td>",
                "text": "",
                "subtableID": -1,
                "surfaceLinks": [],
                "cellID": -1
            }
        ],
        [
            {
                "textTokens": [],
                "isNumeric": true,
                "tdHtmlString": "<td colspan=\"1\" rowspan=\"1\"> 11 </td>",
                "text": "11",
                "subtableID": -1,
                "surfaceLinks": [],
                "cellID": -1
            },
            {
                "textTokens": [],
                "isNumeric": false,
                "tdHtmlString": "<td colspan=\"1\" rowspan=\"1\"> <a href=\"http://www.wikipedia.org/wiki/Melehifo_Uhi\" shape=\"rect\">Melehifo Uhi</a> </td>",
                "text": "Melehifo Uhi",
                "subtableID": -1,
                "surfaceLinks": [
                    {
                        "offset": 0,
                        "target": {
                            "language": "en",
                            "redirecting": false,
                            "id": -1,
                            "title": "Melehifo_Uhi",
                            "namesapce": 0
                        },
                        "isInTemplate": false,
                        "locType": "MAIN_TABLE",
                        "surface": "Melehifo Uhi",
                        "inTemplate": false,
                        "endOffset": 12,
                        "linkType": "INTERNAL_RED"
                    }
                ],
                "cellID": -1
            },
            {
                "textTokens": [],
                "isNumeric": false,
                "tdHtmlString": "<td colspan=\"1\" rowspan=\"1\"> <span>  </span> <a href=\"http://www.wikipedia.org/wiki/Tonga\" shape=\"rect\">Tonga</a> </td>",
                "text": "Tonga",
                "subtableID": -1,
                "surfaceLinks": [
                    {
                        "offset": 0,
                        "target": {
                            "language": "en",
                            "redirecting": false,
                            "id": 30158,
                            "title": "Tonga",
                            "namesapce": 0
                        },
                        "isInTemplate": false,
                        "locType": "MAIN_TABLE",
                        "surface": "Tonga",
                        "inTemplate": false,
                        "endOffset": 5,
                        "linkType": "INTERNAL"
                    }
                ],
                "cellID": -1
            },
            {
                "textTokens": [],
                "isNumeric": true,
                "tdHtmlString": "<td colspan=\"1\" rowspan=\"1\"> 47.52 </td>",
                "text": "47.52",
                "subtableID": -1,
                "surfaceLinks": [],
                "cellID": -1
            },
            {
                "textTokens": [],
                "isNumeric": true,
                "tdHtmlString": "<td colspan=\"1\" rowspan=\"1\"> 49.60 </td>",
                "text": "49.60",
                "subtableID": -1,
                "surfaceLinks": [],
                "cellID": -1
            },
            {
                "textTokens": [],
                "isNumeric": false,
                "tdHtmlString": "<td colspan=\"1\" rowspan=\"1\"> x </td>",
                "text": "x",
                "subtableID": -1,
                "surfaceLinks": [],
                "cellID": -1
            },
            {
                "textTokens": [],
                "isNumeric": false,
                "tdHtmlString": "<td colspan=\"1\" rowspan=\"1\"> </td>",
                "text": "",
                "subtableID": -1,
                "surfaceLinks": [],
                "cellID": -1
            },
            {
                "textTokens": [],
                "isNumeric": false,
                "tdHtmlString": "<td colspan=\"1\" rowspan=\"1\"> </td>",
                "text": "",
                "subtableID": -1,
                "surfaceLinks": [],
                "cellID": -1
            },
            {
                "textTokens": [],
                "isNumeric": false,
                "tdHtmlString": "<td colspan=\"1\" rowspan=\"1\"> </td>",
                "text": "",
                "subtableID": -1,
                "surfaceLinks": [],
                "cellID": -1
            },
            {
                "textTokens": [],
                "isNumeric": true,
                "tdHtmlString": "<td colspan=\"1\" rowspan=\"1\"> 49.60 </td>",
                "text": "49.60",
                "subtableID": -1,
                "surfaceLinks": [],
                "cellID": -1
            },
            {
                "textTokens": [],
                "isNumeric": false,
                "tdHtmlString": "<td colspan=\"1\" rowspan=\"1\"> </td>",
                "text": "",
                "subtableID": -1,
                "surfaceLinks": [],
                "cellID": -1
            }
        ],
        [
            {
                "textTokens": [],
                "isNumeric": true,
                "tdHtmlString": "<td colspan=\"1\" rowspan=\"1\"> 12 </td>",
                "text": "12",
                "subtableID": -1,
                "surfaceLinks": [],
                "cellID": -1
            },
            {
                "textTokens": [],
                "isNumeric": false,
                "tdHtmlString": "<td colspan=\"1\" rowspan=\"1\"> <a href=\"http://www.wikipedia.org/wiki/Mellisa_Gibbons\" shape=\"rect\">Mellisa Gibbons</a> </td>",
                "text": "Mellisa Gibbons",
                "subtableID": -1,
                "surfaceLinks": [
                    {
                        "offset": 0,
                        "target": {
                            "language": "en",
                            "redirecting": false,
                            "id": -1,
                            "title": "Mellisa_Gibbons",
                            "namesapce": 0
                        },
                        "isInTemplate": false,
                        "locType": "MAIN_TABLE",
                        "surface": "Mellisa Gibbons",
                        "inTemplate": false,
                        "endOffset": 15,
                        "linkType": "INTERNAL_RED"
                    }
                ],
                "cellID": -1
            },
            {
                "textTokens": [],
                "isNumeric": false,
                "tdHtmlString": "<td colspan=\"1\" rowspan=\"1\"> <span>  </span> <a href=\"http://www.wikipedia.org/wiki/Jamaica\" shape=\"rect\">Jamaica</a> </td>",
                "text": "Jamaica",
                "subtableID": -1,
                "surfaceLinks": [
                    {
                        "offset": 0,
                        "target": {
                            "language": "en",
                            "redirecting": false,
                            "id": 15660,
                            "title": "Jamaica",
                            "namesapce": 0
                        },
                        "isInTemplate": false,
                        "locType": "MAIN_TABLE",
                        "surface": "Jamaica",
                        "inTemplate": false,
                        "endOffset": 7,
                        "linkType": "INTERNAL"
                    }
                ],
                "cellID": -1
            },
            {
                "textTokens": [],
                "isNumeric": true,
                "tdHtmlString": "<td colspan=\"1\" rowspan=\"1\"> 41.24 </td>",
                "text": "41.24",
                "subtableID": -1,
                "surfaceLinks": [],
                "cellID": -1
            },
            {
                "textTokens": [],
                "isNumeric": true,
                "tdHtmlString": "<td colspan=\"1\" rowspan=\"1\"> 47.38 </td>",
                "text": "47.38",
                "subtableID": -1,
                "surfaceLinks": [],
                "cellID": -1
            },
            {
                "textTokens": [],
                "isNumeric": true,
                "tdHtmlString": "<td colspan=\"1\" rowspan=\"1\"> 44.10 </td>",
                "text": "44.10",
                "subtableID": -1,
                "surfaceLinks": [],
                "cellID": -1
            },
            {
                "textTokens": [],
                "isNumeric": false,
                "tdHtmlString": "<td colspan=\"1\" rowspan=\"1\"> </td>",
                "text": "",
                "subtableID": -1,
                "surfaceLinks": [],
                "cellID": -1
            },
            {
                "textTokens": [],
                "isNumeric": false,
                "tdHtmlString": "<td colspan=\"1\" rowspan=\"1\"> </td>",
                "text": "",
                "subtableID": -1,
                "surfaceLinks": [],
                "cellID": -1
            },
            {
                "textTokens": [],
                "isNumeric": false,
                "tdHtmlString": "<td colspan=\"1\" rowspan=\"1\"> </td>",
                "text": "",
                "subtableID": -1,
                "surfaceLinks": [],
                "cellID": -1
            },
            {
                "textTokens": [],
                "isNumeric": true,
                "tdHtmlString": "<td colspan=\"1\" rowspan=\"1\"> 47.38 </td>",
                "text": "47.38",
                "subtableID": -1,
                "surfaceLinks": [],
                "cellID": -1
            },
            {
                "textTokens": [],
                "isNumeric": false,
                "tdHtmlString": "<td colspan=\"1\" rowspan=\"1\"> </td>",
                "text": "",
                "subtableID": -1,
                "surfaceLinks": [],
                "cellID": -1
            }
        ],
        [
            {
                "textTokens": [],
                "isNumeric": false,
                "tdHtmlString": "<td colspan=\"1\" rowspan=\"1\">  <span> </span> </td>",
                "text": "",
                "subtableID": -1,
                "surfaceLinks": [],
                "cellID": -1
            },
            {
                "textTokens": [],
                "isNumeric": false,
                "tdHtmlString": "<td colspan=\"1\" rowspan=\"1\"> <a href=\"http://www.wikipedia.org/wiki/Emma_Carpenter\" shape=\"rect\">Emma Carpenter</a> </td>",
                "text": "Emma Carpenter",
                "subtableID": -1,
                "surfaceLinks": [
                    {
                        "offset": 0,
                        "target": {
                            "language": "en",
                            "redirecting": false,
                            "id": -1,
                            "title": "Emma_Carpenter",
                            "namesapce": 0
                        },
                        "isInTemplate": false,
                        "locType": "MAIN_TABLE",
                        "surface": "Emma Carpenter",
                        "inTemplate": false,
                        "endOffset": 14,
                        "linkType": "INTERNAL_RED"
                    }
                ],
                "cellID": -1
            },
            {
                "textTokens": [],
                "isNumeric": false,
                "tdHtmlString": "<td colspan=\"1\" rowspan=\"1\"> <span>  </span> <a href=\"http://www.wikipedia.org/wiki/England\" shape=\"rect\">England</a> </td>",
                "text": "England",
                "subtableID": -1,
                "surfaceLinks": [
                    {
                        "offset": 0,
                        "target": {
                            "language": "en",
                            "redirecting": false,
                            "id": 9316,
                            "title": "England",
                            "namesapce": 0
                        },
                        "isInTemplate": false,
                        "locType": "MAIN_TABLE",
                        "surface": "England",
                        "inTemplate": false,
                        "endOffset": 7,
                        "linkType": "INTERNAL"
                    }
                ],
                "cellID": -1
            },
            {
                "textTokens": [],
                "isNumeric": false,
                "tdHtmlString": "<td colspan=\"1\" rowspan=\"1\"> x </td>",
                "text": "x",
                "subtableID": -1,
                "surfaceLinks": [],
                "cellID": -1
            },
            {
                "textTokens": [],
                "isNumeric": false,
                "tdHtmlString": "<td colspan=\"1\" rowspan=\"1\"> x </td>",
                "text": "x",
                "subtableID": -1,
                "surfaceLinks": [],
                "cellID": -1
            },
            {
                "textTokens": [],
                "isNumeric": false,
                "tdHtmlString": "<td colspan=\"1\" rowspan=\"1\"> x </td>",
                "text": "x",
                "subtableID": -1,
                "surfaceLinks": [],
                "cellID": -1
            },
            {
                "textTokens": [],
                "isNumeric": false,
                "tdHtmlString": "<td colspan=\"1\" rowspan=\"1\"> </td>",
                "text": "",
                "subtableID": -1,
                "surfaceLinks": [],
                "cellID": -1
            },
            {
                "textTokens": [],
                "isNumeric": false,
                "tdHtmlString": "<td colspan=\"1\" rowspan=\"1\"> </td>",
                "text": "",
                "subtableID": -1,
                "surfaceLinks": [],
                "cellID": -1
            },
            {
                "textTokens": [],
                "isNumeric": false,
                "tdHtmlString": "<td colspan=\"1\" rowspan=\"1\"> </td>",
                "text": "",
                "subtableID": -1,
                "surfaceLinks": [],
                "cellID": -1
            },
            {
                "textTokens": [],
                "isNumeric": false,
                "tdHtmlString": "<td colspan=\"1\" rowspan=\"1\">  <span> NM</span> </td>",
                "text": "NM",
                "subtableID": -1,
                "surfaceLinks": [],
                "cellID": -1
            },
            {
                "textTokens": [],
                "isNumeric": false,
                "tdHtmlString": "<td colspan=\"1\" rowspan=\"1\"> </td>",
                "text": "",
                "subtableID": -1,
                "surfaceLinks": [],
                "cellID": -1
            }
        ]
    ],
    "order": 0.1830024588853121,
    "numHeaderRows": 1,
    "numCols": 11
}